scy/__init__.py
scy/__main__.py
scy/backend.py
scy/builtins.py
scy/exceptions.py
scy/parser.py
scy/tokenizer.py
scy/tokens.py
scy/utils.py
Scython-0.1.2.dist-info/METADATA
Scython-0.1.2.dist-info/WHEEL
Scython-0.1.2.dist-info/entry_points.txt
Scython-0.1.2.dist-info/top_level.txt
Scython-0.1.2.dist-info/RECORD
