Metadata-Version: 2.1
Name: Scython
Version: 0.1.2
Summary: A C-like alternative syntax parser/front-end for Python
Home-page: https://github.com/Gaming32/Scython
Author: Josiah (Gaming32) Glosson
Author-email: gaming32i64@gmail.com
License: License :: OSI Approved :: MIT License
Platform: UNKNOWN
